{
  "categoryid": {
    "key": "x-com-ibm-ariel.category_id",
    "type": "value",
    "linked": "ariel"
  },
  "username": {
    "key": "user-account.user_id",
    "type": "value"
  },
  "categoryname": {
    "key": "x-com-ibm-ariel.category_name",
    "type": "value",
    "linked": "ariel"
  },
  "logsourceid": {
    "key": "x-com-ibm-ariel.log_source_id",
    "type": "value",
    "linked": "ariel"
  },
  "identityip": {
    "key": "x-com-ibm-ariel.identity_ip",
    "type": "value",
    "linked": "ariel"
  },
  "qidname": {
    "key": "x-com-ibm-ariel.qid_name",
    "type": "value",
    "linked": "ariel"
  },
  "protocolname": {
    "key": "x-com-ibm-ariel.protocol_name",
    "type": "value",
    "linked": "ariel"
  },
  "protocolid": {
    "key": "x-com-ibm-ariel.protocol_id",
    "type": "value",
    "linked": "ariel"
  },
  "destinationip": [
    {
      "key": "ipv4-addr.value",
      "type": "value"
    },
    {
      "key": "ipv6-addr.value",
      "type": "value"
    },
    {
      "key": "network-traffic.dst_ref",
      "type": "reference",
      "linked": "nt",
      "transformer": "ToString"
    }
  ],
  "eventcount": {
    "key": "number_observed",
    "type": "value",
    "transformer": "ToInteger"
  },
  "starttime": [
    {
      "key": "created",
      "type": "value",
      "transformer": "EpochToTimestamp"
    },
    {
      "key": "modified",
      "type": "value",
      "transformer": "EpochToTimestamp"
    },
    {
      "key": "first_observed",
      "type": "value",
      "transformer": "EpochToTimestamp"
    },
    {
      "key": "last_observed",
      "type": "value",
      "transformer": "EpochToTimestamp"
    }
  ],
  "logsourcename": {
    "key": "x-com-ibm-ariel.log_source_name",
    "type": "value",
    "linked": "ariel"
  },
  "magnitude": {
    "key": "x-com-ibm-ariel.magnitude",
    "type": "value",
    "linked": "ariel"
  },
  "sourceip": [
    {
      "key": "ipv4-addr.value",
      "type": "value"
    },
    {
      "key": "ipv6-addr.value",
      "type": "value"
    },
    {
      "key": "network-traffic.src_ref",
      "type": "reference",
      "linked": "nt",
      "transformer": "ToString"
    }
  ],
  "qid": {
    "key": "x-com-ibm-ariel.qid",
    "type": "value",
    "linked": "ariel"
  },
  "url": {
    "key": "url.value",
    "type": "value"
  },
  "domain": {
    "key": "domain-name.value",
    "type": "value"
  },
  "payload": {
    "key": "x-com-ibm-ariel.payload",
    "type": "value",
    "linked": "ariel"
  },
  "destinationport": {
    "key": "network-traffic.dst_port",
    "cybox": "true",
    "linked": "nt",
    "type": "value"
  },
  "sourceport": {
    "key": "network-traffic.src_port",
    "cybox": "true",
    "type": "value",
    "linked": "nt"
  },
  "protocol": {
    "key": "network-traffic.protocols",
    "cybox": "true",
    "type": "value",
    "linked": "nt",
    "transformer": "ToArray"
  }
}
